{"id":"NtpAMVUwRas","title":"Mood","slug":"mood","artwork":"/images/albums/tAzexdC7bsg.jpeg","published_at":"2011-10-31T00:00:00+00:00","artist":{"id":"3oe1RSE7pik","title":"Evil Needle"},"catalogNumber":"S005","links":[{"href":"https://www.amazon.co.uk/Mood-Music/dp/B0725W6WRY?tag=soulectiontracklists-21","platform":"amazonMusic"},{"href":"https://music.apple.com/us/album/mood/1169142120?at=1010lMz4","platform":"appleMusic"},{"href":"https://soulection.bandcamp.com/album/mood","platform":"bandcamp"},{"href":"https://soundcloud.com/bastardjazz/09-evil-needle-mood-music","platform":"soundcloud"},{"href":"https://open.spotify.com/album/1sQOKQaTSGzndHXOZeus9n","platform":"spotify"},{"href":"https://open.spotify.com/album/1sQOKQaTSGzndHXOZeus9n","platform":"spotify"},{"href":"https://gumroad.com/l/jzTQ/love?wanted=true","platform":"gumroad"}],"content":"As promised, Soulection is back with our 5th release for the month of October. We weren't kidding when we stated last month that we would really be dropping a release on you for the next 6+ months straight. Continuing on with our monthly-series of releases, Evil Needle -– all the way from France really impressed us with this album. It’s simply entitled, Mood and you’ll hear why in just a bit. \n\nEvil Needle has been producing for 5 years now & has a very distinct sound that represents various soundscapes of what we call Future-Soul. Mood has this smooth & deep vibe that triggers the mind into deep-thought mode. He has a consistent style and impeccable selection of sound placement... Whether it’s his precise drums, smooth bass-lines, intricate keys or crispy snares, he always manages to place and layer every sound with perfection. Mood is 14 tracks deep and it is full of cinematic and soulful vibrations that will get your energy up. Enjoy this one! \n\nCredits: \n06. Rendez-Vous (Co-Produced by Sivey) \nSivey : www.soundcloud.com/sivey \n\n13. Climax (Co-Produced by Broad Rush) \nBroad Rush : www.soundcloud.com/broad-rush \n\nArtwork by Jason Alfred-Palmer \ncargocollective.com/jasonalfredpalmer \n\nEvil Needle's Contact Info: \nsoundcloud.com/evilneedleprod \n\ntwitter.com/itsmeneedle","tags":["album"],"state":"published"}