{"links":{"soundcloud":"https://soundcloud.com/soulection/soulection-radio-show-239-w-anderson-paak"},"title":"Soulection Radio Show #239 w/ Anderson .Paak","artwork":"/images/episodes/239.jpg","slug":"239","duration":7209,"chapters":[{"title":"Joe Kay’s Session","artwork":null,"markers":[{"id":"gG-tLBijEYY","track":{"id":"nYAF6180Zcw","path":"/artists/caleb-alleyne/tracks/saturday/","title":"SATURDAY","artist":{"id":"uMT_JUwmPrY","title":"caleb alleyne"},"artwork":null},"rawTrack":"caleb alleyne - SATURDAY","timestamp":null},{"id":"GXCqKvIFU_A","track":{"id":"SDozP19OLwE","path":"/artists/dutchboy/tracks/west-ting/","title":"West Ting","artist":{"id":"M7EZd0hyxOw","title":"Dutchboy"},"artwork":"images/artists/dutchboy/tracks/west-ting.jpg"},"rawTrack":"_dutchboy - West Ting","timestamp":null},{"id":"LfL45TyPHJQ","track":{"id":"CAaDsXCVWcI","path":"/artists/jordan-manswell/tracks/two/","title":"Two","artist":{"id":"jimzYSRIvTE","title":"Jordan Manswell"},"artwork":null},"rawTrack":"Jordan Manswell - Two","timestamp":null},{"id":"LpB0684bCS4","track":{"id":"x6Ah_U8bUqE","path":"/artists/pyrmdplaza/tracks/pyrmdplaza/","title":"pyrmdplaza","artist":{"id":"FRoCGg6cO3w","title":"Pyrmdplaza"},"artwork":null},"rawTrack":"PYRMDPLAZA - pyrmdplaza - fhior","timestamp":null},{"id":"7HTW-O_FLeQ","track":{"id":"Nw2LuEkW30g","path":"/artists/gravez/tracks/stay-tough-feat-jmsn-elhae/","title":"Stay Tough (feat. Jmsn & Elhae)","artist":{"id":"zW5m-32JlvM","title":"gravez"},"artwork":"images/artists/gravez/tracks/stay-tough-feat-jmsn-elhae.jpg"},"rawTrack":"Gravez - Stay Tough (feat. Jmsn & Elhae)","timestamp":null},{"id":"vMiYmQf1olM","track":{"id":"n9zQubwpLtI","path":"/artists/penthouse-penthouse/tracks/stilettos/","title":"stilettos","artist":{"id":"PF9sQweNVys","title":"Penthouse Penthouse"},"artwork":"images/artists/penthouse-penthouse/tracks/stilettos.jpg"},"rawTrack":"Penthouse Penthouse - stilettos","timestamp":null},{"id":"ifMJ5Fj9UOA","track":{"id":"KNgzvJv_-Q8","path":"/artists/bob-james-earl-klugh/tracks/the-sponge/","title":"The Sponge","artist":{"id":"9ra2lL93DyI","title":"Bob James & Earl Klugh"},"artwork":"images/artists/bob-james-earl-klugh/tracks/the-sponge.jpg"},"rawTrack":"Bob James & Earl Klugh - The Sponge","timestamp":null},{"id":"5JnlY7HG5VU","track":{"id":"D67pQUSkuuY","path":"/artists/nas/tracks/watch-dem-niggas/","title":"Watch Dem Niggas","artist":{"id":"bdYk1PtVG7w","title":"Nas"},"artwork":"images/artists/nas/tracks/watch-dem-niggas.jpg"},"rawTrack":"Nas - Watch Dem Niggas","timestamp":null},{"id":"4V4vzlBjQBE","track":{"id":"bAyJNMNWt9E","path":"/artists/breezy-lovejoy/tracks/p-y-p-acoustic-version/","title":"P.Y.P (Acoustic Version)","artist":{"id":"aJiaGD-7Qn8","title":"Breezy Lovejoy"},"artwork":"images/artists/breezy-lovejoy/tracks/p-y-p-acoustic-version.jpg"},"rawTrack":"Breezy Lovejoy - P.Y.P (Acoustic Version)","timestamp":null},{"id":"RLkU-rLFhL0","track":{"id":"gLLF3APg-LI","path":"/artists/d-angelo/tracks/me-those-dreamin-eyes-jay-dee-remix/","title":"Me Those Dreamin Eyes (Jay Dee Remix)","artist":{"id":"nmTKZKnLYCQ","title":"D'Angelo"},"artwork":"images/artists/d-angelo/tracks/me-those-dreamin-eyes-jay-dee-remix.jpg"},"rawTrack":"D'Angelo - Me Those Dreamin Eyes (Jay Dee Remix)","timestamp":null},{"id":"ZdsAEXAzPZM","track":{"id":"6JAsOKKL8AQ","path":"/artists/d-angelo/tracks/smooth/","title":"Smooth","artist":{"id":"nmTKZKnLYCQ","title":"D'Angelo"},"artwork":"images/artists/d-angelo/tracks/smooth.jpg"},"rawTrack":"D'Angelo - Smooth","timestamp":null},{"id":"LaprBVTGAZU","track":{"id":"qcEkFcGqDQE","path":"/artists/eugene-wilde/tracks/gotta-get-you-home-tonight/","title":"Gotta Get You Home Tonight","artist":{"id":"IaTybIQvfNY","title":"Eugene Wilde"},"artwork":"images/artists/eugene-wilde/tracks/gotta-get-you-home-tonight.jpg"},"rawTrack":"Eugene Wilde - Gotta Get You Home Tonight","timestamp":null},{"id":"RGXbP--ar-k","track":{"id":"ErEdji-jhyQ","path":"/artists/foxy-brown/tracks/get-me-home/","title":"Get Me Home","artist":{"id":"ymfQw2grmOQ","title":"Foxy Brown"},"artwork":"images/artists/foxy-brown/tracks/get-me-home.jpg"},"rawTrack":"Foxy Brown - Get Me Home","timestamp":null},{"id":"rKtA54bea1E","track":{"id":"dVEdKbjYPbc","path":"/artists/lamont-dozier/tracks/interlude/","title":"Interlude","artist":{"id":"zV4YHpxSr4s","title":"Lamont Dozier"},"artwork":"images/artists/lamont-dozier/tracks/interlude.jpg"},"rawTrack":"Lamont Dozier - Interlude","timestamp":null},{"id":"JCb_-XVjNkA","track":{"id":"2vUD-NdBQS8","path":"/artists/talib-kweli-madlib/tracks/soul-music/","title":"Soul Music","artist":{"id":"w5KczaRnU0I","title":"Talib Kweli & Madlib"},"artwork":"images/artists/talib-kweli-madlib/tracks/soul-music.png"},"rawTrack":"Talib Kweli & Madlib - Soul Music","timestamp":null},{"id":"Ji_w4a3kTUM","track":{"id":"SV7HwEKPNsY","path":"/artists/dwele/tracks/swank-feat-monica-blaire/","title":"Swank (feat. Monica Blaire)","artist":{"id":"Sm8jNDkuWaA","title":"Dwele"},"artwork":"images/artists/dwele/tracks/swank-feat-monica-blaire.jpg"},"rawTrack":"Dwele - Swank (feat. Monica Blaire)","timestamp":null},{"id":"knQaoWK8U_k","track":{"id":"RwIJFxtdi9I","path":"/artists/joey-badass/tracks/hillary-wank-prod-by-lee-bannon/","title":"Hillary $wank [Prod. By Lee Bannon]","artist":{"id":"rkp6Ayuv2QQ","title":"Joey Bada$$"},"artwork":null},"rawTrack":"Joey Bada$$ - Hillary $wank [Prod. By Lee Bannon]","timestamp":null},{"id":"cqB8q-FmlEs","track":{"id":"uwiY7pauO48","path":"/artists/zebrahim/tracks/zoning/","title":"zoning","artist":{"id":"PS3fQtpNQts","title":"Zebrahim"},"artwork":"images/artists/zebrahim/tracks/zoning.png"},"rawTrack":"zebrahim - zoning","timestamp":null},{"id":"We-MK2KICP8","track":{"id":"7iPa4nzrL4Y","path":"/artists/zebrahim/tracks/zoology/","title":"zoology","artist":{"id":"PS3fQtpNQts","title":"Zebrahim"},"artwork":"images/artists/zebrahim/tracks/zoology.png"},"rawTrack":"zebrahim - zoology","timestamp":null},{"id":"hGbbJ4MpBBI","track":{"id":"U_ewFt-dz1Q","path":"/artists/kendrick-lamar/tracks/for-free-interlude/","title":"For Free? (Interlude)","artist":{"id":"jx4O4_qN86c","title":"Kendrick Lamar"},"artwork":"images/artists/kendrick-lamar/tracks/for-free-interlude.jpg"},"rawTrack":"Kendrick Lamar - For Free? (Interlude)","timestamp":null},{"id":"ZvwES3U-VNM","track":{"id":"bxhkyUQUs9U","path":"/artists/chance-the-rapper/tracks/somewhere-in-paradise-feat-jeremih-r-kelly/","title":"Somewhere in Paradise (feat. Jeremih & R. Kelly)","artist":{"id":"oVJtBxB1YAs","title":"Chance The Rapper"},"artwork":"images/artists/chance-the-rapper/tracks/somewhere-in-paradise-feat-jeremih-r-kelly.jpg"},"rawTrack":"Chance The Rapper - Somewhere in Paradise (feat. Jeremih & R. Kelly)","timestamp":null},{"id":"S24rycbXyws","track":{"id":"qG4O8n-19gI","path":"/artists/n-e-r-d/tracks/run-to-the-sun/","title":"Run To The Sun","artist":{"id":"1Xk624n5ZSs","title":"N.E.R.D"},"artwork":"images/artists/n-e-r-d/tracks/run-to-the-sun.jpg"},"rawTrack":"N*E*R*D - Run To The Sun","timestamp":null},{"id":"7TrJFCJy-PI","track":{"id":"tpxByNGoihA","path":"/artists/teeza/tracks/funny-money/","title":"Funny Money","artist":{"id":"cj2wmkjekos","title":"Teeza"},"artwork":"images/artists/teeza/tracks/funny-money.jpg"},"rawTrack":"Teeza - Funny Money","timestamp":null},{"id":"Xe7Z5To5-z8","track":{"id":"E_VIrQIhYgw","path":"/artists/trashbat/tracks/takaramachi/","title":"Takaramachi","artist":{"id":"N-4C7RJhXjM","title":"Trashbat"},"artwork":"images/artists/trashbat/tracks/takaramachi.png"},"rawTrack":"Trashbat - Takaramachi","timestamp":null},{"id":"mfOY97xcfjg","track":{"id":"INh4pPEvb9U","path":"/artists/flying-lotus/tracks/getting-there-ft-niki-randa/","title":"Getting There ft. Niki Randa","artist":{"id":"HFm2hlk4lcQ","title":"Flying Lotus"},"artwork":"images/artists/flying-lotus/tracks/getting-there-ft-niki-randa.jpg"},"rawTrack":"Flying Lotus - Getting There ft. Niki Randa","timestamp":null},{"id":"pvhG99gV3XE","track":{"id":"6eR4q6oV2bY","path":"/artists/joey-badass/tracks/sweet-dreams/","title":"Sweet Dreams","artist":{"id":"rkp6Ayuv2QQ","title":"Joey Bada$$"},"artwork":null},"rawTrack":"Joey Bada$$ - Sweet Dreams","timestamp":null},{"id":"zpztoAaYCHs","track":null,"rawTrack":" - ","timestamp":null},{"id":"wqqpL9vHuvQ","track":{"id":"evw2k8_dzX0","path":"/artists/the-roots/tracks/mellow-my-man/","title":"Mellow My Man","artist":{"id":"5-Ce1_rqz78","title":"The Roots"},"artwork":"images/artists/the-roots/tracks/mellow-my-man.jpg"},"rawTrack":"The Roots - Mellow My Man","timestamp":null},{"id":"mTV02vXUSDk","track":{"id":"ZuDJUpxt6SA","path":"/artists/snoop-dogg/tracks/beautiful-ft-hidden-beach-records/","title":"Beautiful ft. Hidden Beach Records","artist":{"id":"0LC7awnLg04","title":"Snoop Dogg"},"artwork":"images/artists/snoop-dogg/tracks/beautiful-ft-hidden-beach-records.png"},"rawTrack":"Snoop Dogg - Beautiful ft. Hidden Beach Records","timestamp":null},{"id":"H9e5YoPB0AU","track":{"id":"cNp7LjO9z2E","path":"/artists/zebrahim/tracks/zilch/","title":"Zilch","artist":{"id":"PS3fQtpNQts","title":"Zebrahim"},"artwork":"images/artists/zebrahim/tracks/zilch.jpg"},"rawTrack":"zebrahim - zilch","timestamp":null},{"id":"qe3__H9kylw","track":{"id":"CAQEsWxmXIs","path":"/artists/hi-tek/tracks/det-ta-steppin/","title":"Det Ta Steppin'","artist":{"id":"vfHBRp_8MgI","title":"Hi-Tek"},"artwork":"images/artists/hi-tek/tracks/det-ta-steppin.png"},"rawTrack":"Hi-Tek - Det Ta Steppin'","timestamp":null},{"id":"1pLRWuANPAg","track":{"id":"QVlL_zqm_k8","path":"/artists/jordon-manswell/tracks/tiller/","title":"Tiller","artist":{"id":"CyeepK8egiU","title":"Jordon Manswell"},"artwork":"images/artists/jordon-manswell/tracks/tiller.jpg"},"rawTrack":"Jordon Manswell - Tiller","timestamp":null},{"id":"gUxJOUuKSr4","track":{"id":"N1lidDWHLWw","path":"/artists/ola/tracks/girl-code-rmx/","title":"Girl code Rmx","artist":{"id":"Y1KJ7WiOx_E","title":"Ola"},"artwork":"images/artists/ola/tracks/girl-code-rmx.png"},"rawTrack":"Ola - Girl code Rmx","timestamp":null},{"id":"2jN2-PeW6aw","track":{"id":"RmQqQW8vi-o","path":"/artists/neguim/tracks/we-dancin/","title":"We Dancin","artist":{"id":"y07ojm8K0tw","title":"Neguim"},"artwork":"images/artists/neguim/tracks/we-dancin.jpg"},"rawTrack":"Neguim. - We Dancin","timestamp":null},{"id":"BDwrlOqY1tE","track":{"id":"2B-305ko9xg","path":"/artists/eric-coleman/tracks/islands/","title":"Islands","artist":{"id":"cUcp_v_p_m8","title":"Eric Coleman"},"artwork":"images/artists/eric-coleman/tracks/islands.jpg"},"rawTrack":"Eric Coleman - Islands","timestamp":null},{"id":"1Xnf8sACSuQ","track":{"id":"L-G9BXQ6xmk","path":"/artists/j-dilla/tracks/think-twice/","title":"Think Twice","artist":{"id":"JCLTKJoRpXE","title":"J Dilla"},"artwork":"images/artists/j-dilla/tracks/think-twice.jpg"},"rawTrack":"J Dilla - Think Twice","timestamp":null},{"id":"SfStp2Rn1Qs","track":{"id":"6perxe6F770","path":"/artists/butcherbrownva/tracks/the-blast-talib-kweli-and-hi/","title":"The Blast (Talib Kweli and Hi","artist":{"id":"DAHIP2S9X4g","title":"ButcherBrownVA"},"artwork":"images/artists/butcherbrownva/tracks/the-blast-talib-kweli-and-hi.jpg"},"rawTrack":"ButcherBrownVA - The Blast (Talib Kweli and Hi - ","timestamp":null},{"id":"0giEAXIPTKU","track":{"id":"BXBvIMhnSFw","path":"/artists/talib-kweli-hi-tek/tracks/just-begun-feat-jay-electronica-j-cole-and-mos-def/","title":"Just Begun (feat. Jay Electronica, J. Cole and Mos Def)","artist":{"id":"wkQBw06OsJ0","title":"Talib Kweli & Hi-Tek"},"artwork":"images/artists/talib-kweli-hi-tek/tracks/just-begun-feat-jay-electronica-j-cole-and-mos-def.jpg"},"rawTrack":"Talib Kweli & Hi-Tek - Just Begun (feat. Jay Electronica, J. Cole and Mos Def)","timestamp":null},{"id":"L5snpPgWmus","track":{"id":"z4MauVL1zo8","path":"/artists/mos-def/tracks/boogie-man-song/","title":"Boogie Man Song","artist":{"id":"uBIe5-hEAGs","title":"Mos Def"},"artwork":"images/artists/mos-def/tracks/boogie-man-song.jpg"},"rawTrack":"Mos Def - Boogie Man Song","timestamp":null},{"id":"Q-LeBlabwI0","track":{"id":"keXIIvtjJZ4","path":"/artists/afta-1-cazeaux-oslo/tracks/marvelous-magical-jackobious-son-a-sweaterless/","title":"Marvelous Magical Jackobious Son (A Sweaterless","artist":{"id":"v0s_M-YqFPo","title":"AFTA-1 & Cazeaux Oslo"},"artwork":"images/artists/afta-1-cazeaux-oslo/tracks/marvelous-magical-jackobious-son-a-sweaterless.png"},"rawTrack":"AFTA-1 & Cazeaux Oslo - Marvelous Magical Jackobious Son (A Sweaterless","timestamp":null},{"id":"vkUL3JNKJxI","track":{"id":"dD_dTODU2gU","path":"/artists/taylor-mcferrin/tracks/greene-sun/","title":"Greene Sun","artist":{"id":"DTqMujJ2cAc","title":"Taylor McFerrin"},"artwork":"images/artists/taylor-mcferrin/tracks/greene-sun.jpg"},"rawTrack":"Taylor McFerrin - Greene Sun","timestamp":null},{"id":"8xwgfIY0v1I","track":{"id":"AL2rRdFK574","path":"/artists/breezy-lovejoy/tracks/p-y-p-acoustic/","title":"P.Y.P. (Acoustic)","artist":{"id":"aJiaGD-7Qn8","title":"Breezy Lovejoy"},"artwork":"images/artists/breezy-lovejoy/tracks/p-y-p-acoustic.jpg"},"rawTrack":"Breezy Lovejoy - P.Y.P. (Acoustic)","timestamp":null},{"id":"lxoo9E8_uPQ","track":{"id":"pRirgzGogwA","path":"/artists/breezy-lovejoy/tracks/p-y-p-carmack-edit/","title":"P.Y.P. (Carmack Edit)","artist":{"id":"aJiaGD-7Qn8","title":"Breezy Lovejoy"},"artwork":"images/artists/breezy-lovejoy/tracks/p-y-p-carmack-edit.jpg"},"rawTrack":"Breezy Lovejoy - P.Y.P. (Carmack Edit)","timestamp":null},{"id":"N1XmVLQiA_U","track":{"id":"ddSbLNFfpi0","path":"/artists/teeza/tracks/brela/","title":"Brela","artist":{"id":"cj2wmkjekos","title":"Teeza"},"artwork":"images/artists/teeza/tracks/brela.jpg"},"rawTrack":"Teeza - Brela","timestamp":null},{"id":"LPciicKTz5M","track":{"id":"Uhyez83OWNI","path":"/artists/nxworries/tracks/suede/","title":"Suede","artist":{"id":"YurhOxq2_MA","title":"NxWorries"},"artwork":"images/artists/nxworries/tracks/suede.jpg"},"rawTrack":"Nxworries - Suede","timestamp":null},{"id":"NwLBizZXikk","track":{"id":"SeNl3qFWUYQ","path":"/artists/evans/tracks/room-404/","title":"Room 404","artist":{"id":"AnwrEKZy5ig","title":"Evans"},"artwork":null},"rawTrack":"Evans - Room 404","timestamp":null}]}]}