{"links":{"appleMusic":"https://music.apple.com/gb/station/episode-533/ra.1599610128","soundcloud":"https://soundcloud.com/soulection/soulection-radio-show-533"},"title":"Soulection Radio Show #533 (Rich Medina Takeover)","artwork":"images/episodes/soulection-radio-show-533.jpg","slug":"533","duration":7200,"chapters":[{"title":"Rich Medina's Session","artwork":null,"markers":[{"id":"_wYYR6onl2I","track":{"id":"1FELFLIMS84","path":"/artists/funk-inc/tracks/goodbye-so-long/","title":"Goodbye, So Long","artist":{"id":"F_IddxF3DYg","title":"Funk Inc."},"artwork":"images/artists/funk-inc/tracks/goodbye-so-long.jpg"},"rawTrack":"Funk Inc. - Goodbye, So Long","timestamp":"00:00:19"},{"id":"-k49ImIUs90","track":{"id":"aq4qPr2_-Bk","path":"/artists/gregory-porter/tracks/musical-genocide/","title":"Musical Genocide","artist":{"id":"oCuJb2dyrFI","title":"Gregory Porter"},"artwork":"images/artists/gregory-porter/tracks/musical-genocide.jpg"},"rawTrack":"Gregory Porter - Musical Genocide","timestamp":"00:03:59"},{"id":"1S7L4uLiOQo","track":{"id":"LYdwEq2ZuL8","path":"/artists/raphael-saadiq/tracks/chic-feat-teedra-moses/","title":"Chic (feat. Teedra Moses)","artist":{"id":"Iue_45Ckqe8","title":"Raphael Saadiq"},"artwork":"images/artists/raphael-saadiq/tracks/chic-feat-teedra-moses.jpg"},"rawTrack":"Raphael Saadiq - Chic (feat. Teedra Moses)","timestamp":"00:06:58"},{"id":"nLK0y5kT_mE","track":{"id":"VRFffmQAcMI","path":"/artists/erykah-badu/tracks/love-of-my-life-kaytranada-remix/","title":"Love of My Life (Kaytranada Remix)","artist":{"id":"dD9L38eJbIk","title":"Erykah Badu"},"artwork":null},"rawTrack":"Erykah Badu - Love Of My Life (Kaytranada Remix)","timestamp":"00:10:15"},{"id":"AUJOIiI6HNM","track":{"id":"Pz34bqn4URc","path":"/artists/anderson-paak/tracks/6-summers/","title":"6 Summers","artist":{"id":"Xi3SzrRL6Xg","title":"Anderson .Paak"},"artwork":"images/artists/anderson-paak/tracks/6-summers.jpg"},"rawTrack":"Anderson .Paak - 6 Summers","timestamp":"00:12:21"},{"id":"x4wf4IALhRo","track":{"id":"SrR92kOxeug","path":"/artists/hiatus-kaiyote/tracks/get-sun-feat-arthur-verocai/","title":"Get Sun (feat. Arthur Verocai)","artist":{"id":"Vac6QXc95pU","title":"Hiatus Kaiyote"},"artwork":"images/artists/hiatus-kaiyote/tracks/get-sun-feat-arthur-verocai.jpg"},"rawTrack":"Hiatus Kaiyote - Get Sun (feat. Arthur Verocai)","timestamp":"00:14:44"},{"id":"PYeW6IojIpE","track":{"id":"p7X4ovwINZQ","path":"/artists/j-davey/tracks/might-as-well/","title":"Might As Well","artist":{"id":"kPq-QOleGko","title":"J*Davey"},"artwork":"images/artists/j-davey/tracks/might-as-well.jpg"},"rawTrack":"J*Davey - Might As Well","timestamp":"00:18:53"},{"id":"b8pFJ7cC2Ko","track":{"id":"NvZauLAhDuI","path":"/artists/tall-black-guy/tracks/give-me-a-chance/","title":"Give Me A Chance","artist":{"id":"IuSZ-0drVP8","title":"Tall Black Guy"},"artwork":null},"rawTrack":"Tall Black Guy - Give Me A Chance","timestamp":"00:22:37"},{"id":"brsOySbD16Q","track":{"id":"gKhDELKVPd0","path":"/artists/the-jacksons/tracks/dancing-machine-daniel-crawford-remix/","title":"Dancing Machine (Daniel Crawford Remix)","artist":{"id":"dZwMsDntJF0","title":"The Jacksons"},"artwork":"images/artists/the-jacksons/tracks/dancing-machine-daniel-crawford-remix.jpg"},"rawTrack":"The Jacksons - Dancing Machine (Daniel Crawford Remix)","timestamp":"00:25:02"},{"id":"pg5OJ_-E2Y8","track":{"id":"aBeyAhJJZAE","path":"/artists/fonzworth-bentley/tracks/everybody-feat-kanye-west-andr-3000/","title":"Everybody (feat. Kanye West & André 3000)","artist":{"id":"bRxD6BQUHp8","title":"Fonzworth Bentley"},"artwork":"images/artists/fonzworth-bentley/tracks/everybody-feat-kanye-west-andr-3000.jpg"},"rawTrack":"Fonzworth Bentley - Everybody (feat. Kanye West & André 3000)","timestamp":"00:28:04"},{"id":"BL5EMgWOK48","track":{"id":"oB-wH6N4yek","path":"/artists/stro-elliott/tracks/feel-4-chaka/","title":"Feel 4 Chaka","artist":{"id":"6fpn2yMnMxQ","title":"Stro Elliott"},"artwork":"images/artists/stro-elliott/tracks/feel-4-chaka.jpg"},"rawTrack":"Stro Elliott - Feel 4 Chaka","timestamp":"00:30:53"},{"id":"dc2O1Csh92U","track":{"id":"_vccZZQhUMM","path":"/artists/the-roots/tracks/the-ultimate-live/","title":"The Ultimate (Live)","artist":{"id":"5-Ce1_rqz78","title":"The Roots"},"artwork":"images/artists/the-roots/tracks/the-ultimate-live.jpg"},"rawTrack":"The Roots - The Ultimate (Live)","timestamp":"00:36:41"},{"id":"1fCu6e4bGjY","track":{"id":"8zTV4r53dio","path":"/artists/busta-rhymes/tracks/wheel-of-fortune/","title":"Wheel of Fortune","artist":{"id":"C0u7BUAzfQE","title":"Busta Rhymes"},"artwork":"images/artists/busta-rhymes/tracks/wheel-of-fortune.jpg"},"rawTrack":"Busta Rhymes - Wheel of Fortune","timestamp":"00:38:58"},{"id":"V1BAzwL9j4U","track":{"id":"9LcSvyzp5Eo","path":"/artists/q-tip/tracks/renaissance-rap-remix-feat-busta-raekwon-lil-wayne/","title":"Renaissance Rap Remix (feat. Busta, Raekwon, Lil Wayne)","artist":{"id":"x9rLA996TVg","title":"Q-Tip"},"artwork":null},"rawTrack":"Q-Tip - Renaissance Rap Remix (feat. Busta, Raekwon, Lil Wayne)","timestamp":"00:41:19"},{"id":"uwHyNAjO5xU","track":{"id":"ltq89Ta1TbM","path":"/artists/the-sylvers/tracks/misdemeanor-dk-edit/","title":"Misdemeanor (DK Edit)","artist":{"id":"lXRq27v_NMg","title":"The Sylvers"},"artwork":null},"rawTrack":"The Sylvers - Misdemeanor (DK Edit)","timestamp":"00:44:37"},{"id":"RudF45430ps","track":{"id":"LegEu8YWo4k","path":"/artists/misdemeanor-dk-edit-the-sylvers/tracks/engine-9-the-reflex-edit/","title":"Engine #9 (The Reflex Edit)","artist":{"id":"jktWVLgH_bY","title":"Misdemeanor (DK Edit), The Sylvers"},"artwork":null},"rawTrack":"Misdemeanor (DK Edit), The Sylvers - Engine #9 (The Reflex Edit)","timestamp":"00:46:41"},{"id":"RPD2f2y_dsQ","track":{"id":"8h1gjQa9EXA","path":"/artists/wlson-pickett/tracks/engine-9-the-reflex-edit/","title":"Engine #9 (The Reflex Edit)","artist":{"id":"hLm75iia8U4","title":"Wlson Pickett"},"artwork":"images/artists/wlson-pickett/tracks/engine-9-the-reflex-edit.jpg"},"rawTrack":"Wlson Pickett - Engine #9 (The Reflex Edit)","timestamp":"00:46:43"},{"id":"XDCJ2jBt5IM","track":{"id":"t9N1gON38qA","path":"/artists/sweet-charles/tracks/hang-out-and-hustle/","title":"Hang out and Hustle","artist":{"id":"Lj3SesCjMyU","title":"Sweet Charles"},"artwork":"images/artists/sweet-charles/tracks/hang-out-and-hustle.jpg"},"rawTrack":"Sweet Charles - Hang out and Hustle","timestamp":"00:49:27"},{"id":"kb0O4mhMmZY","track":{"id":"Csy79aZoR3s","path":"/artists/stro-elliot/tracks/soul-ii-stro/","title":"Soul II Stro","artist":{"id":"7lENSeopd2Y","title":"Stro Elliot"},"artwork":"images/artists/stro-elliot/tracks/soul-ii-stro.jpg"},"rawTrack":"Stro Elliot - Soul II Stro","timestamp":"00:53:25"},{"id":"5r33rt6_mDg","track":{"id":"JdJODjMgRFA","path":"/artists/nas/tracks/the-world-is-yours-dj-heron-edit/","title":"The World Is Yours (DJ Heron Edit)","artist":{"id":"bdYk1PtVG7w","title":"Nas"},"artwork":null},"rawTrack":"Nas - The World Is Yours (DJ Heron Edit)","timestamp":"00:56:45"},{"id":"PbyeOgWMigM","track":{"id":"5rCEPZfvg18","path":"/artists/the-pharcyde/tracks/runnin-j-rocc-po-edit/","title":"Runnin’ (J Rocc PO Edit)","artist":{"id":"6e1YGdvo4Sc","title":"The Pharcyde"},"artwork":null},"rawTrack":"The Pharcyde - Runnin’ (J Rocc PO Edit)","timestamp":"01:02:39"},{"id":"MSU-PJO_SNQ","track":{"id":"lynIF0KkVqk","path":"/artists/waajeed/tracks/jeedo-suave/","title":"Jeedo Suave","artist":{"id":"3ZlMxidIue0","title":"Waajeed"},"artwork":null},"rawTrack":"Waajeed - Jeedo Suave","timestamp":"01:07:19"},{"id":"9NQzaVF0l0I","track":{"id":"uww9TyHZD4A","path":"/artists/the-blackbyrds/tracks/reggins/","title":"Reggins","artist":{"id":"m539ujrJTCM","title":"The Blackbyrds"},"artwork":"images/artists/the-blackbyrds/tracks/reggins.jpg"},"rawTrack":"The Blackbyrds - Reggins","timestamp":"01:11:00"},{"id":"rJjO_gK5R6M","track":{"id":"ZC4SUbJ9f8Q","path":"/artists/the-headhunters/tracks/i-remember-i-made-you-crazy/","title":"I Remember I Made You Crazy","artist":{"id":"W9eFGH1qKVY","title":"The Headhunters"},"artwork":null},"rawTrack":"AWB - I Remember I Made You Cry","timestamp":"01:14:17"},{"id":"TvjuoWlir0E","track":{"id":"SrbyOP3-IS4","path":"/artists/joe-farrell/tracks/upon-this-rock/","title":"Upon This Rock","artist":{"id":"00DsOEEQG_Q","title":"Joe Farrell"},"artwork":"images/artists/joe-farrell/tracks/upon-this-rock.jpg"},"rawTrack":"Joe Farrell - Upon This Rock","timestamp":"01:16:51"},{"id":"QKXfKIsgK5o","track":{"id":"UM6uItHkeSE","path":"/artists/james-brown/tracks/mind-power/","title":"Mind Power","artist":{"id":"tqyochfkjXk","title":"James Brown"},"artwork":"images/artists/james-brown/tracks/mind-power.jpg"},"rawTrack":"James Brown - Mind Power","timestamp":"01:19:38"},{"id":"clz3k_Lswfw","track":{"id":"gDSE65JjmAE","path":"/artists/fela-kuti/tracks/it-s-no-possible/","title":"It's No Possible","artist":{"id":"AxLciSkoeU4","title":"Fela Kuti"},"artwork":"images/artists/fela-kuti/tracks/it-s-no-possible.jpg"},"rawTrack":"Fela Kuti - It's No Possible","timestamp":"01:29:32"},{"id":"JuBZi99NJiQ","track":{"id":"0FtSQcnJLmM","path":"/artists/soulection-radio-hosted-by-rich-medina/tracks/it-s-no-possible/","title":"It's No Possible","artist":{"id":"ImVuqsmuQeo","title":"Soulection Radio, Hosted by Rich Medina"},"artwork":null},"rawTrack":"Soulection Radio, Hosted by Rich Medina - It's No Possible","timestamp":"01:45:06"},{"id":"epuQt_9bs-E","track":{"id":"gDSE65JjmAE","path":"/artists/fela-kuti/tracks/it-s-no-possible/","title":"It's No Possible","artist":{"id":"AxLciSkoeU4","title":"Fela Kuti"},"artwork":"images/artists/fela-kuti/tracks/it-s-no-possible.jpg"},"rawTrack":"Fela Kuti - It's No Possible","timestamp":"01:45:08"},{"id":"all0CB2r62I","track":{"id":"x39mWJ0YuIY","path":"/artists/ledisi/tracks/feeling-orange/","title":"Feeling Orange","artist":{"id":"U5AzzmkEjEk","title":"Ledisi"},"artwork":null},"rawTrack":"Ledisi - Feeling Orange","timestamp":"01:48:25"}]}]}