{"links":{"appleMusic":"https://music.apple.com/us/station/episode-583/ra.1672433860","soundcloud":"https://soundcloud.com/soulection/583livefromjt"},"title":"Soulection Radio Show #583","artwork":"images/episodes/soulection-radio-show-583.jpg","slug":"583","duration":7200,"chapters":[{"title":"Joe Kay's Session","artwork":null,"markers":[{"id":"94a_j1e8WsM","track":{"id":"dmNGe7FUba8","path":"/artists/hosted-by-joe-kay/tracks/soulection-radio/","title":"Soulection Radio","artist":{"id":"9iA9GLfZi7U","title":"Hosted by Joe Kay"},"artwork":""},"rawTrack":"Hosted by Joe Kay - Soulection Radio","timestamp":"00:00:02"},{"id":"P80NPQ7gjC0","track":{"id":"JGxSDaF2lqc","path":"/artists/el/tracks/nautilus-interlude-89bpm/","title":"Nautilus Interlude [89bpm]","artist":{"id":"dyRBuBCSPsQ","title":"el."},"artwork":"images/artists/el/tracks/nautilus-interlude-89bpm.jpg"},"rawTrack":"el. - Nautilus Interlude [89bpm]","timestamp":"00:00:20"},{"id":"GW0f7QoqCyE","track":{"id":"yzTJuwG3hHc","path":"/artists/mack-keane-esta/tracks/rowlin/","title":"rowlin","artist":{"id":"eGU5HyDcid0","title":"Mack Keane & ESTA."},"artwork":null},"rawTrack":"Mack Keane & ESTA. - rowlin","timestamp":"00:01:45"},{"id":"d1XYD3D_-Pc","track":{"id":"L-G9BXQ6xmk","path":"/artists/j-dilla/tracks/think-twice/","title":"Think Twice","artist":{"id":"JCLTKJoRpXE","title":"J Dilla"},"artwork":"images/artists/j-dilla/tracks/think-twice.jpg"},"rawTrack":"J Dilla - Think Twice","timestamp":"00:02:59"},{"id":"gZ2mHX1ORDw","track":{"id":"A1dmLUIMkHY","path":"/artists/modha/tracks/lions-cowards-feat-phabo/","title":"Lions & Cowards (feat. Phabo)","artist":{"id":"lEet4pUrGLM","title":"Modha"},"artwork":"images/artists/modha/tracks/lions-cowards-feat-phabo.jpg"},"rawTrack":"Modha - Lions & Cowards (feat. Phabo)","timestamp":"00:23:19"},{"id":"ntUbx7aDNN0","track":{"id":"oC27lJ7bmfU","path":"/artists/sir/tracks/nothing-greater/","title":"Nothing Greater","artist":{"id":"Mm0LvYfmWsg","title":"SiR"},"artwork":"images/artists/sir/tracks/nothing-greater.jpg"},"rawTrack":"Sir - Nothing Greater","timestamp":"00:25:27"},{"id":"7OLCT5MFDUU","track":{"id":"o1pTG9TpBL0","path":"/artists/larry-june-the-alchemist/tracks/60-days/","title":"60 Days","artist":{"id":"0fSTgNPK4M4","title":"Larry June & The Alchemist"},"artwork":"images/artists/larry-june-the-alchemist/tracks/60-days.jpg"},"rawTrack":"Larry June & The Alchemist - 60 Days","timestamp":"00:28:23"},{"id":"DV6gVzIF8-4","track":{"id":"RknLpxGujvw","path":"/artists/tyler-the-creator/tracks/group-b/","title":"GROUP B","artist":{"id":"zM8QZPzUldc","title":"Tyler, The Creator"},"artwork":"images/artists/tyler-the-creator/tracks/group-b.jpg"},"rawTrack":"Tyler, The Creator - GROUP B","timestamp":"00:30:12"},{"id":"UhsgLfbWLwg","track":{"id":"iKDvxZ0XxbY","path":"/artists/drew-s-theory/tracks/what-you-see-feat-mr-emmanuel/","title":"What You See (feat. Mr. Emmanuel)","artist":{"id":"fOXyoSH564A","title":"Drew's Theory"},"artwork":"images/artists/drew-s-theory/tracks/what-you-see-feat-mr-emmanuel.jpg"},"rawTrack":"Drew's Theory - What You See (feat. Mr. Emmanuel)","timestamp":"00:44:37"},{"id":"KV6ShM0wLFU","track":{"id":"SpMb3TORas0","path":"/artists/mad-keys/tracks/something-different/","title":"Something Different","artist":{"id":"Wu894xro02E","title":"Mad Keys"},"artwork":"images/artists/mad-keys/tracks/something-different.jpg"},"rawTrack":"Mad Keys - Something Different","timestamp":"01:01:55"},{"id":"YvX50I4PNBQ","track":{"id":"DScpBtJHGl8","path":"/artists/domi-jd-beck/tracks/whatup/","title":"WHATUP","artist":{"id":"_632NI-qmRM","title":"DOMi & JD BECK"},"artwork":"images/artists/domi-jd-beck/tracks/whatup.jpg"},"rawTrack":"DOMi & JD BECK - WHATUP","timestamp":"01:03:31"},{"id":"qFeMKSs69pg","track":{"id":"CrXDOqNQ1NI","path":"/artists/yussef-dayes/tracks/raisins-under-the-sun-desert-version-live-at-joshua-tree/","title":"Raisins Under the Sun (Desert Version) [Live at Joshua Tree]","artist":{"id":"7HrW4JqYqZ0","title":"Yussef Dayes"},"artwork":"images/artists/yussef-dayes/tracks/raisins-under-the-sun-desert-version-live-at-joshua-tree.jpg"},"rawTrack":"Yussef Dayes - Raisins Under the Sun (Desert Version) [Live at Joshua Tree]","timestamp":"01:05:40"},{"id":"zKYa38vI-5Q","track":{"id":"vmA4sHM32x8","path":"/artists/joyce-wrice/tracks/bittersweet-goodbyes/","title":"Bittersweet Goodbyes","artist":{"id":"9wcdi9hQWvw","title":"Joyce Wrice"},"artwork":"images/artists/joyce-wrice/tracks/bittersweet-goodbyes.jpg"},"rawTrack":"Joyce Wrice - Bittersweet Goodbyes","timestamp":"01:09:02"},{"id":"r3wLsZxF7eA","track":{"id":"PU327GbTcVw","path":"/artists/wizkid/tracks/2-sugar-feat-ayra-starr-joe-kay-s-slowed-edit/","title":"2 Sugar (feat. Ayra Starr) [Joe Kay's Slowed Edit]","artist":{"id":"k3Rt5QjxDqU","title":"Wizkid"},"artwork":null},"rawTrack":"Wizkid - 2 Sugar (feat. Ayra Starr) [Joe Kay's Slowed Edit]","timestamp":"01:11:59"},{"id":"5XHhwgjMQn4","track":{"id":"3wNFIkn4_uA","path":"/artists/wizkid/tracks/fever/","title":"Fever","artist":{"id":"k3Rt5QjxDqU","title":"Wizkid"},"artwork":"images/artists/wizkid/tracks/fever.jpg"},"rawTrack":"Wizkid - Fever","timestamp":"01:13:49"},{"id":"ypPhvDWrfpM","track":{"id":"ciLpOL5yZ_Q","path":"/artists/burna-boy/tracks/cloak-dagger-feat-j-hus-juls-remix/","title":"Cloak & Dagger (feat. J. Hus) [Juls Remix]","artist":{"id":"yMZLyK5402g","title":"Burna Boy"},"artwork":"images/artists/burna-boy/tracks/cloak-dagger-feat-j-hus-juls-remix.jpg"},"rawTrack":"Burna Boy - Cloak & Dagger (feat. J. Hus) [Juls Remix]","timestamp":"01:16:18"},{"id":"xuNCNQc2-aU","track":{"id":"SEb1RqF42h4","path":"/artists/egnever/tracks/show-me-what-you-got-xxxtrumpet/","title":"Show Me What You Got / XXXTRUMPET","artist":{"id":"wotYTWxjPwg","title":"egnever"},"artwork":"images/artists/egnever/tracks/show-me-what-you-got-xxxtrumpet.jpg"},"rawTrack":"egnever - Show Me What You Got / XXXTRUMPET","timestamp":"01:17:29"},{"id":"z5lFXEaWUpc","track":{"id":"pfPLLBZFFbM","path":"/artists/felo-le-tee-x-mellow-sleazy/tracks/midnight-prayer/","title":"Midnight Prayer","artist":{"id":"xVXxp12huU0","title":"Felo Le Tee x Mellow & Sleazy"},"artwork":"images/artists/felo-le-tee-x-mellow-sleazy/tracks/midnight-prayer.jpg"},"rawTrack":"Felo Le Tee x Mellow & Sleazy - Midnight Prayer","timestamp":"01:20:19"},{"id":"4RMSIBbgrNc","track":{"id":"hQ8Grh7DGw8","path":"/artists/jvkinho/tracks/voc-e-a-luz/","title":"Você e a luz","artist":{"id":"mtNUs5Jy2O8","title":"JVKINHO"},"artwork":"images/artists/jvkinho/tracks/voc-e-a-luz.jpg"},"rawTrack":"JVKINHO - Você e a luz","timestamp":"01:23:02"},{"id":"rH4vVC5-9W0","track":{"id":"K2PQHUXMLgc","path":"/artists/geotheory/tracks/yur-luv-boom-room-mixxx/","title":"Yur Luv (BOOM ROOM MIXXX)","artist":{"id":"xjRAuQbWw_c","title":"GEOTHEORY"},"artwork":"images/artists/geotheory/tracks/yur-luv-boom-room-mixxx.jpg"},"rawTrack":"GEOTHEORY - Yur Luv (BOOM ROOM MIXXX)","timestamp":"01:24:50"},{"id":"p1xiGvBN3Kk","track":{"id":"dmNGe7FUba8","path":"/artists/hosted-by-joe-kay/tracks/soulection-radio/","title":"Soulection Radio","artist":{"id":"9iA9GLfZi7U","title":"Hosted by Joe Kay"},"artwork":""},"rawTrack":"Hosted by Joe Kay - Soulection Radio","timestamp":"01:27:26"},{"id":"gF9x_8AW57A","track":{"id":"5N_Z5jtbwX4","path":"/artists/wilfy-d/tracks/2-good-2-be-true-ld-mix/","title":"2 Good 2 Be True (LD Mix)","artist":{"id":"Hik2xLJvXJI","title":"Wilfy D"},"artwork":"images/artists/wilfy-d/tracks/2-good-2-be-true-ld-mix.jpg"},"rawTrack":"Wilfy D - 2 Good 2 Be True (LD Mix)","timestamp":"01:27:42"},{"id":"bLNquE201g4","track":{"id":"iaoor2XuxC0","path":"/artists/tiptoes/tracks/somebody/","title":"Somebody","artist":{"id":"wTokxGERMSo","title":"Tiptoes"},"artwork":"images/artists/tiptoes/tracks/somebody.jpg"},"rawTrack":"Tiptoes - Somebody","timestamp":"01:30:00"},{"id":"7zC5lVUi84w","track":{"id":"cEoyosA4UHQ","path":"/artists/wax/tracks/80008a/","title":"80008A","artist":{"id":"7qwTHT55bl0","title":"Wax"},"artwork":"images/artists/wax/tracks/80008a.jpg"},"rawTrack":"Wax - 80008A","timestamp":"01:32:08"},{"id":"NiGB3jbLYq4","track":{"id":"wO8DiPCWuIw","path":"/artists/wax/tracks/80008b/","title":"80008B","artist":{"id":"7qwTHT55bl0","title":"Wax"},"artwork":"images/artists/wax/tracks/80008b.jpg"},"rawTrack":"Wax - 80008B","timestamp":"01:34:40"},{"id":"WurMNSaA5Go","track":{"id":"2njlVy57tsU","path":"/artists/midland/tracks/final-credits/","title":"Final Credits","artist":{"id":"Ps6ioq0TnrM","title":"Midland"},"artwork":"images/artists/midland/tracks/final-credits.jpg"},"rawTrack":"Midland - Final Credits","timestamp":"01:37:13"},{"id":"Tfy_z8b57yI","track":{"id":"rk6N3DFKz6c","path":"/artists/everything-but-the-girl/tracks/tracey-in-my-room-lazy-dog-bootleg-vocal-mix/","title":"Tracey in My Room (Lazy Dog Bootleg Vocal Mix)","artist":{"id":"ERCnSRlvT7E","title":"Everything But the Girl"},"artwork":"images/artists/everything-but-the-girl/tracks/tracey-in-my-room-lazy-dog-bootleg-vocal-mix.jpg"},"rawTrack":"Everything But the Girl - Tracey in My Room (Lazy Dog Bootleg Vocal Mix)","timestamp":"01:40:21"},{"id":"BYpRuAQCUt4","track":{"id":"Z0leC5KyiFY","path":"/artists/chaos-in-the-cbd-lee-pearson-jr-collective/tracks/it-s-up-to-me-feat-k-ladawn-joe-armon-jones-instrumental/","title":"It's up to Me (feat. K LaDawn & Joe Armon-Jones) [Instrumental]","artist":{"id":"rZl2EU-ga5s","title":"Chaos In The CBD & Lee Pearson Jr Collective"},"artwork":"images/artists/chaos-in-the-cbd-lee-pearson-jr-collective/tracks/it-s-up-to-me-feat-k-ladawn-joe-armon-jones-instrumental.jpg"},"rawTrack":"Chaos In The CBD & Lee Pearson Jr Collective - It's up to Me (feat. K LaDawn & Joe Armon-Jones) [Instrumental]","timestamp":"01:43:34"},{"id":"jdvP_ZfcTKU","track":{"id":"PxDddFomiqk","path":"/artists/dj-mabooku-cdm/tracks/merengue/","title":"MERENGUE","artist":{"id":"tqBKY8soisI","title":"Dj MaBoOku CDM"},"artwork":"images/artists/dj-mabooku-cdm/tracks/merengue.jpg"},"rawTrack":"Dj MaBoOku CDM - MERENGUE","timestamp":"01:46:19"},{"id":"_G9RXQ38BJg","track":{"id":"aG4F8IZQU4M","path":"/artists/lokowat/tracks/ponto-suspeito/","title":"Ponto Suspeito","artist":{"id":"vYXZQcwki_Y","title":"Lokowat"},"artwork":"images/artists/lokowat/tracks/ponto-suspeito.jpg"},"rawTrack":"Lokowat - Ponto Suspeito","timestamp":"01:48:35"},{"id":"JBzzHcrTso8","track":{"id":"-HomBpymLfY","path":"/artists/sango/tracks/trem-bala-da-congo/","title":"Trem Bala Da Congo","artist":{"id":"Ttil0zVanis","title":"Sango"},"artwork":"images/artists/sango/tracks/trem-bala-da-congo.jpg"},"rawTrack":"Sango - Trem Bala Da Congo","timestamp":"01:50:19"},{"id":"aKxVh7VULp0","track":{"id":"Y7zAb0m5gjA","path":"/artists/sango/tracks/engenho-da-rainha-feat-carlos-complexo/","title":"Engenho da Rainha (feat. Carlos & Complexo)","artist":{"id":"Ttil0zVanis","title":"Sango"},"artwork":"images/artists/sango/tracks/engenho-da-rainha-feat-carlos-complexo.jpg"},"rawTrack":"Sango - Engenho da Rainha (feat. Carlos & Complexo)","timestamp":"01:51:12"},{"id":"NR9T-Eumo9s","track":{"id":"dmNGe7FUba8","path":"/artists/hosted-by-joe-kay/tracks/soulection-radio/","title":"Soulection Radio","artist":{"id":"9iA9GLfZi7U","title":"Hosted by Joe Kay"},"artwork":""},"rawTrack":"Hosted by Joe Kay - Soulection Radio","timestamp":"01:53:39"},{"id":"P3pZiJ8cJhU","track":{"id":"ozqKjvS4-3M","path":"/artists/jlz/tracks/sento-com-as-colega/","title":"sento com as colega","artist":{"id":"8dVRDUKaXJE","title":"JLZ"},"artwork":null},"rawTrack":"JLZ - sento com as colega","timestamp":"01:54:28"},{"id":"eVKuj1yac8I","track":{"id":"MtrmQdFCF0c","path":"/artists/children-of-zeus/tracks/the-most-humblest-of-all-time-ever/","title":"The Most Humblest of All Time, Ever","artist":{"id":"3zGEz2W3Q_U","title":"Children of Zeus"},"artwork":"images/artists/children-of-zeus/tracks/the-most-humblest-of-all-time-ever.jpg"},"rawTrack":"Children of Zeus - The Most Humblest of All Time, Ever","timestamp":"01:54:37"},{"id":"PRGzQg-cLw8","track":{"id":"I-MrobVp5hY","path":"/artists/sans/tracks/nothing-like-lovin-u/","title":"nothing like lovin' u","artist":{"id":"KeK5MMiDz84","title":"sans"},"artwork":"images/artists/sans/tracks/nothing-like-lovin-u.jpg"},"rawTrack":"sans - nothing like lovin' u","timestamp":"01:57:59"},{"id":"nkKD55_Xr_c","track":{"id":"s_2ojmV32xg","path":"/artists/sonder/tracks/drive-u-crazy/","title":"Drive U Crazy","artist":{"id":"GFac3i-BR1c","title":"Sonder"},"artwork":"images/artists/sonder/tracks/drive-u-crazy.jpg"},"rawTrack":"Sonder - Drive U Crazy","timestamp":"01:59:06"}]}]}